README.md
setup.py
exp_notifier.egg-info/PKG-INFO
exp_notifier.egg-info/SOURCES.txt
exp_notifier.egg-info/dependency_links.txt
exp_notifier.egg-info/requires.txt
exp_notifier.egg-info/top_level.txt
notifier/__init__.py
notifier/context.py
notifier/slack.py
notifier/bin/__init__.py
notifier/bin/ntf
notifier/bin/send-msg-todo.py
notifier/bin/socket-monitor.py