Metadata-Version: 2.1
Name: exp-notifier
Version: 0.0.2
Summary: Notifcation from experiments to you devices (via slack)
Home-page: https://github.com/oplatek/exp-notifier
Author: Ondrej Platek
Author-email: ondrej.platek@seznam.cz
License: Apache-2.0 License
Platform: UNKNOWN
Classifier: Development Status :: 3 - Alpha
Classifier: Intended Audience :: Developers
Classifier: Topic :: System :: Logging
Classifier: Topic :: System :: Networking :: Monitoring
Classifier: License :: OSI Approved :: Apache Software License
Classifier: Programming Language :: Python :: 3.6
Classifier: Programming Language :: Python :: 3.7
Classifier: Programming Language :: Python :: 3.8
Classifier: Programming Language :: Python :: 3.9
Requires-Python: >=3.6.0
